nasdaq_news_crawler/__init__.py
nasdaq_news_crawler/config.py
nasdaq_news_crawler/data_source.py
nasdaq_news_crawler/pipeline.py
nasdaq_news_crawler/scraper.py
nasdaq_news_crawler/sentiment_analyzer.py
nasdaq_news_crawler-0.6.0.dist-info/LICENSE
nasdaq_news_crawler-0.6.0.dist-info/METADATA
nasdaq_news_crawler-0.6.0.dist-info/WHEEL
nasdaq_news_crawler-0.6.0.dist-info/top_level.txt
nasdaq_news_crawler-0.6.0.dist-info/RECORD
