Metadata-Version: 2.1
Name: nasdaq-news-crawler
Version: 0.6.0
Summary: A tool for scraping and analyzing news and press releases from NASDAQ-listed companies.
Author: Norbert Nieżorawski
Author-email: norbertnnn@gmail.com
License: MIT
Classifier: Intended Audience :: Developers
Classifier: License :: OSI Approved :: MIT License
Classifier: Programming Language :: Python :: 3
Classifier: Programming Language :: Python :: 3.10
Classifier: Programming Language :: Python :: 3.11
Classifier: Operating System :: OS Independent
Requires-Python: >=3.10
License-File: LICENSE
Requires-Dist: pandas
Requires-Dist: beautifulsoup4
Requires-Dist: requests
Requires-Dist: tqdm
Requires-Dist: selenium
Requires-Dist: transformers
Requires-Dist: torch
Requires-Dist: python-dateutil
